Metadata-Version: 1.0
Name: easyhelloworld
Version: 1.0
Summary: Hello World
Home-page: UNKNOWN
Author: UNKNOWN
Author-email: easyhelloworld228@gmail.com
License: UNKNOWN
Platform: UNKNOWN
